cdk_use_cases/custom_cloud9_ssm/__init__.py
cdk_use_cases/custom_cloud9_ssm/py.typed
cdk_use_cases/custom_cloud9_ssm/_jsii/__init__.py
cdk_use_cases/custom_cloud9_ssm/_jsii/custom-cloud9-ssm@1.4.0.jsii.tgz
cdk_use_cases.custom_cloud9_ssm-1.4.0.data/scripts/custom-cloud9-ssm
cdk_use_cases.custom_cloud9_ssm-1.4.0.dist-info/LICENSE
cdk_use_cases.custom_cloud9_ssm-1.4.0.dist-info/METADATA
cdk_use_cases.custom_cloud9_ssm-1.4.0.dist-info/WHEEL
cdk_use_cases.custom_cloud9_ssm-1.4.0.dist-info/top_level.txt
cdk_use_cases.custom_cloud9_ssm-1.4.0.dist-info/RECORD
