Metadata-Version: 2.1
Name: cdk-use-cases.custom-cloud9-ssm
Version: 1.4.0
Summary: Pattern for Cloud9 EC2 environment and SSM Document.
Home-page: https://github.com/aws-samples/cdk-use-cases.git
Author: Borja Pérez Guasch
License: Apache-2.0
Project-URL: Source, https://github.com/aws-samples/cdk-use-cases.git
Platform: UNKNOWN
Classifier: Intended Audience :: Developers
Classifier: Operating System :: OS Independent
Classifier: Programming Language :: JavaScript
Classifier: Programming Language :: Python :: 3 :: Only
Classifier: Programming Language :: Python :: 3.8
Classifier: Programming Language :: Python :: 3.9
Classifier: Programming Language :: Python :: 3.10
Classifier: Programming Language :: Python :: 3.11
Classifier: Typing :: Typed
Classifier: Development Status :: 4 - Beta
Classifier: License :: OSI Approved
Requires-Python: ~=3.8
License-File: LICENSE
Requires-Dist: aws-cdk-lib (<3.0.0,>=2.135.0)
Requires-Dist: constructs (<11.0.0,>=10.3.0)
Requires-Dist: jsii (<2.0.0,>=1.97.0)
Requires-Dist: publication (>=0.0.3)
Requires-Dist: typeguard (~=2.13.3)
